{
  "project_info": {
    "project_number": "449945112655",
    "project_id": "bakery-dcd5e",
    "storage_bucket": "bakery-dcd5e.appspot.com"
  },
  "client": [
    {
      "client_info": {
        "mobilesdk_app_id": "1:449945112655:android:92d2cdb8c1646dcac51a3a",
        "android_client_info": {
          "package_name": "com.uth.bakeryapp"
        }
      },
      "oauth_client": [
        {
          "client_id": "449945112655-40kssf055rb8pjcimumd14k804fsuo96.apps.googleusercontent.com",
          "client_type": 3
        }
      ],
      "api_key": [
        {
          "current_key": "AIzaSyD391gYZlmKu8Z6FSWVLn7pE9YeBbRUF4I"
        }
      ],
      "services": {
        "appinvite_service": {
          "other_platform_oauth_client": [
            {
              "client_id": "449945112655-40kssf055rb8pjcimumd14k804fsuo96.apps.googleusercontent.com",
              "client_type": 3
            }
          ]
        }
      }
    },
    {
      "client_info": {
        "mobilesdk_app_id": "1:449945112655:android:b71e519a14c3d2e2c51a3a",
        "android_client_info": {
          "package_name": "com.uth.bakeryapp"
        }
      },
      "oauth_client": [
        {
          "client_id": "449945112655-40kssf055rb8pjcimumd14k804fsuo96.apps.googleusercontent.com",
          "client_type": 3
        }
      ],
      "api_key": [
        {
          "current_key": "AIzaSyD391gYZlmKu8Z6FSWVLn7pE9YeBbRUF4I"
        }
      ],
      "services": {
        "appinvite_service": {
          "other_platform_oauth_client": [
            {
              "client_id": "449945112655-40kssf055rb8pjcimumd14k804fsuo96.apps.googleusercontent.com",
              "client_type": 3
            }
          ]
        }
      }
    }
  ],
  "configuration_version": "1"
}